libre_chat/__init__.py
libre_chat/__main__.py
libre_chat/conf.py
libre_chat/endpoint.py
libre_chat/llm.py
libre_chat/py.typed
libre_chat/router.py
libre_chat/ui.py
libre_chat/utils.py
libre_chat/static/web-worker.js
libre_chat/templates/admin.html
libre_chat/templates/index.html
libre_chat/webapp/favicon.ico
libre_chat/webapp/index.html
libre_chat/webapp/index.html.br
libre_chat/webapp/index.html.gz
libre_chat/webapp/_build/manifest.json
libre_chat/webapp/_build/manifest.json.br
libre_chat/webapp/_build/manifest.json.gz
libre_chat/webapp/_build/server-functions-manifest.json
libre_chat/webapp/_build/assets/_...404_-8a5712b0.js
libre_chat/webapp/_build/assets/about-cf4c1418.js
libre_chat/webapp/_build/assets/app-2bb1f2bd.js
libre_chat/webapp/_build/assets/app-2bb1f2bd.js.br
libre_chat/webapp/_build/assets/app-2bb1f2bd.js.gz
libre_chat/webapp/_build/assets/app-cc63fe87.css
libre_chat/webapp/_build/assets/app-cc63fe87.css.br
libre_chat/webapp/_build/assets/app-cc63fe87.css.gz
libre_chat/webapp/_build/assets/client-710add3a.js
libre_chat/webapp/_build/assets/client-710add3a.js.br
libre_chat/webapp/_build/assets/client-710add3a.js.gz
libre_chat/webapp/_build/assets/components-70d2ff75.js
libre_chat/webapp/_build/assets/index-683459cb.js
libre_chat/webapp/_build/assets/index-683459cb.js.br
libre_chat/webapp/_build/assets/index-683459cb.js.gz
libre_chat/webapp/_build/assets/routing-e8757775.js
libre_chat/webapp/_build/assets/routing-e8757775.js.br
libre_chat/webapp/_build/assets/routing-e8757775.js.gz
libre_chat/webapp/assets/components-86ea9901.js
libre_chat/webapp/assets/components-86ea9901.js.br
libre_chat/webapp/assets/components-86ea9901.js.gz
libre_chat/webapp/assets/index-cc63fe87.css
libre_chat/webapp/assets/index-cc63fe87.css.br
libre_chat/webapp/assets/index-cc63fe87.css.gz
libre_chat/webapp/assets/routes-52c4f9a3.js
libre_chat/webapp/assets/routes-52c4f9a3.js.br
libre_chat/webapp/assets/routes-52c4f9a3.js.gz
libre_chat/webapp/public/favicon.ico
libre_chat-0.0.6.dist-info/METADATA
libre_chat-0.0.6.dist-info/WHEEL
libre_chat-0.0.6.dist-info/entry_points.txt
libre_chat-0.0.6.dist-info/licenses/LICENSE.txt
libre_chat-0.0.6.dist-info/RECORD
