Metadata-Version: 2.1
Name: libre-chat
Version: 0.0.6
Summary: Free and Open Source Large Language Model (LLM) chatbot web UI and API. Self-hosted, offline capable and easy to setup. Powered by LangChain and Llama 2.
Project-URL: Homepage, https://github.com/vemonet/libre-chat
Project-URL: Documentation, https://github.com/vemonet/libre-chat
Project-URL: History, https://github.com/vemonet/libre-chat/releases
Project-URL: Tracker, https://github.com/vemonet/libre-chat/issues
Project-URL: Source, https://github.com/vemonet/libre-chat
Author-email: Vincent Emonet <vincent.emonet@gmail.com>
Maintainer-email: Vincent Emonet <vincent.emonet@gmail.com>
License: MIT License
License-File: LICENSE.txt
Keywords: Python
Classifier: License :: OSI Approved :: MIT License
Classifier: Operating System :: OS Independent
Classifier: Programming Language :: Python :: 3
Classifier: Programming Language :: Python :: 3.8
Classifier: Programming Language :: Python :: 3.9
Classifier: Programming Language :: Python :: 3.10
Classifier: Programming Language :: Python :: 3.11
Requires-Python: >=3.8
Requires-Dist: faiss-cpu>=1.7.4
Requires-Dist: fastapi
Requires-Dist: gradio>=4.0.0
Requires-Dist: gunicorn
Requires-Dist: jinja2
Requires-Dist: langchain
Requires-Dist: langchain-community
Requires-Dist: llama-cpp-python
Requires-Dist: pydantic-settings
Requires-Dist: pydantic-yaml
Requires-Dist: pydantic>=2.0.0
Requires-Dist: pypdf
Requires-Dist: requests
Requires-Dist: sentence-transformers
Requires-Dist: tqdm
Requires-Dist: typer>=0.6.0
Requires-Dist: unstructured
Requires-Dist: uvicorn
Provides-Extra: doc
Requires-Dist: mdx-include>=1.4.1; extra == 'doc'
Requires-Dist: mkdocs-markdownextradata-plugin>=0.2.5; extra == 'doc'
Requires-Dist: mkdocs-material>=8.2.7; extra == 'doc'
Requires-Dist: mkdocs-open-in-new-tab; extra == 'doc'
Requires-Dist: mkdocs>=1.4.2; extra == 'doc'
Requires-Dist: mkdocstrings[python]>=0.19.1; extra == 'doc'
Provides-Extra: gpu
Requires-Dist: faiss-gpu; extra == 'gpu'
Provides-Extra: test
Requires-Dist: httpx; extra == 'test'
Requires-Dist: mypy>=1.4.1; extra == 'test'
Requires-Dist: pip-tools; extra == 'test'
Requires-Dist: pre-commit; extra == 'test'
Requires-Dist: pytest-asyncio; extra == 'test'
Requires-Dist: pytest-cov>=3.0.0; extra == 'test'
Requires-Dist: pytest>=7.4.0; extra == 'test'
Requires-Dist: types-requests; extra == 'test'
Requires-Dist: types-setuptools; extra == 'test'
Provides-Extra: windows
Requires-Dist: python-magic-bin; extra == 'windows'
